nncf/__init__.py
nncf/definitions.py
nncf/errors.py
nncf/parameters.py
nncf/scopes.py
nncf/version.py
nncf/api/__init__.py
nncf/api/compression.py
nncf/api/statistics.py
nncf/common/__init__.py
nncf/common/check_features.py
nncf/common/collector.py
nncf/common/composite_compression.py
nncf/common/compression.py
nncf/common/deprecation.py
nncf/common/engine.py
nncf/common/exporter.py
nncf/common/factory.py
nncf/common/hook_handle.py
nncf/common/insertion_point_graph.py
nncf/common/plotting.py
nncf/common/schedulers.py
nncf/common/scopes.py
nncf/common/stateful_classes_registry.py
nncf/common/statistics.py
nncf/common/strip.py
nncf/common/tensor.py
nncf/common/accuracy_aware_training/__init__.py
nncf/common/accuracy_aware_training/runner.py
nncf/common/accuracy_aware_training/runner_factory.py
nncf/common/accuracy_aware_training/statistics.py
nncf/common/accuracy_aware_training/training_loop.py
nncf/common/graph/__init__.py
nncf/common/graph/definitions.py
nncf/common/graph/graph.py
nncf/common/graph/graph_matching.py
nncf/common/graph/layer_attributes.py
nncf/common/graph/model_transformer.py
nncf/common/graph/operator_metatypes.py
nncf/common/graph/utils.py
nncf/common/graph/patterns/__init__.py
nncf/common/graph/patterns/manager.py
nncf/common/graph/patterns/patterns.py
nncf/common/graph/transformations/__init__.py
nncf/common/graph/transformations/command_creation.py
nncf/common/graph/transformations/commands.py
nncf/common/graph/transformations/layout.py
nncf/common/hardware/__init__.py
nncf/common/hardware/config.py
nncf/common/hardware/opset.py
nncf/common/hardware/configs/cpu.json
nncf/common/hardware/configs/gpu.json
nncf/common/hardware/configs/npu.json
nncf/common/hardware/configs/template.md
nncf/common/initialization/__init__.py
nncf/common/initialization/batchnorm_adaptation.py
nncf/common/initialization/dataloader.py
nncf/common/logging/__init__.py
nncf/common/logging/logger.py
nncf/common/logging/progress_bar.py
nncf/common/logging/track_progress.py
nncf-2.18.0.dist-info/licenses/LICENSE
nncf-2.18.0.dist-info/METADATA
nncf-2.18.0.dist-info/WHEEL
nncf-2.18.0.dist-info/top_level.txt
nncf-2.18.0.dist-info/RECORD
