Metadata-Version: 2.4
Name: nncf
Version: 2.18.0
Summary: Neural Networks Compression Framework
Author: Intel
Author-email: maksim.proshin@intel.com
License-Expression: Apache-2.0
Project-URL: Homepage, https://github.com/openvinotoolkit/nncf
Keywords: bert,classification,compression,hawq,mixed-precision-training,mmdetection,nas,nlp,object-detection,pruning,quantization,quantization-aware-training,semantic-segmentation,sparsity,transformers
Classifier: Operating System :: OS Independent
Classifier: Programming Language :: Python :: 3
Requires-Python: >=3.9
License-File: LICENSE
Requires-Dist: jsonschema>=3.2.0
Requires-Dist: natsort>=7.1.0
Requires-Dist: networkx<3.5.0,>=2.6
Requires-Dist: ninja<1.14,>=1.10.0.post2
Requires-Dist: numpy<2.3.0,>=1.24.0
Requires-Dist: openvino-telemetry>=2023.2.0
Requires-Dist: packaging>=20.0
Requires-Dist: pandas<2.4,>=1.1.5
Requires-Dist: psutil
Requires-Dist: pydot<=3.0.4,>=1.4.1
Requires-Dist: pymoo>=0.6.0.1
Requires-Dist: rich>=13.5.2
Requires-Dist: safetensors>=0.4.1
Requires-Dist: scikit-learn>=0.24.0
Requires-Dist: scipy>=1.3.2
Requires-Dist: tabulate>=0.9.0
Provides-Extra: plots
Requires-Dist: kaleido>=0.2.1; extra == "plots"
Requires-Dist: matplotlib>=3.3.4; extra == "plots"
Requires-Dist: pillow>=9.0.0; extra == "plots"
Requires-Dist: plotly-express>=0.4.1; extra == "plots"
Dynamic: license-file
